
<?xml version="1.0" encoding="UTF-8"?>
<openerp>
  <data>

    <template id="report_invoice_extra">
      <t t-call="report.html_container">
        <t t-foreach="doc_ids" t-as="doc_id">
          <t t-raw="translate_doc(doc_id, doc_model, 'partner_id.lang', 'bts.report_invoice_document_extra_org')"/>
        </t>
      </t>
    </template>
    <template id="report_invoice_extra_2">
      <t t-call="report.html_container">
        <t t-foreach="doc_ids" t-as="doc_id">
          <t t-raw="translate_doc(doc_id, doc_model, 'partner_id.lang', 'bts.report_invoice_document_extra_cop')"/>
        </t>
      </t>
    </template>
  </data>
</openerp>

